{
  "theorem_name": "succ_add_succ_4",
  "theorem_statement": "\n\u22a2 \u2200 (a b : Nat), a.succ + b.succ = (a + b).succ.succ",
  "file_path": "lean4-example",
  "status": "Failed",
  "proof": null,
  "total_time": 6.2706298828125,
  "actor_time": 6.268305540084839,
  "environment_time": 0.002209186553955078,
  "num_total_nodes": 6,
  "num_searched_nodes": 6,
  "search_tree": {
    "node_type": "InternalNode",
    "state_text": "\n\u22a2 \u2200 (a b : Nat), a.succ + b.succ = (a + b).succ.succ",
    "tactic": null,
    "step_logprob": 0.0,
    "cumulative_logprob": 0.0,
    "depth": 0,
    "ppl": null,
    "order_of_expansion": 0,
    "error_message": null,
    "children": [
      {
        "node_type": "ErrorNode",
        "state_text": null,
        "tactic": "theorem succ_add_succ (a b : Nat) : a.succ + b.succ = (a + b).succ.succ := by",
        "step_logprob": -0.058282663745264855,
        "cumulative_logprob": -0.058282663745264855,
        "depth": 1,
        "ppl": 1.060014581058852,
        "order_of_expansion": 1,
        "error_message": "{'hasSorry': False, 'hasUnsafe': False, 'parseError': \"<Pantograph>:1:0: expected '{' or tactic\"}",
        "children": []
      },
      {
        "node_type": "ErrorNode",
        "state_text": null,
        "tactic": "theorem succ_add_succ_eq_succ_succ_add (a b : Nat) : a.succ + b.succ = (a + b).succ.succ := by",
        "step_logprob": -0.10913261694785877,
        "cumulative_logprob": -0.10913261694785877,
        "depth": 1,
        "ppl": 1.1153102495754728,
        "order_of_expansion": 2,
        "error_message": "{'hasSorry': False, 'hasUnsafe': False, 'parseError': \"<Pantograph>:1:0: expected '{' or tactic\"}",
        "children": []
      },
      {
        "node_type": "ErrorNode",
        "state_text": null,
        "tactic": "theorem step1 : \u2200 (a b : Nat), a.succ + b.succ = (a + b).succ.succ := by",
        "step_logprob": -0.15309504539735855,
        "cumulative_logprob": -0.15309504539735855,
        "depth": 1,
        "ppl": 1.165435742982136,
        "order_of_expansion": 3,
        "error_message": "{'hasSorry': False, 'hasUnsafe': False, 'parseError': \"<Pantograph>:1:0: expected '{' or tactic\"}",
        "children": []
      },
      {
        "node_type": "ErrorNode",
        "state_text": null,
        "tactic": "`intro a b",
        "step_logprob": -0.918461799621582,
        "cumulative_logprob": -0.918461799621582,
        "depth": 1,
        "ppl": 2.505433565553756,
        "order_of_expansion": 4,
        "error_message": "{'hasSorry': False, 'hasUnsafe': False, 'parseError': \"<Pantograph>:1:0: expected '{' or tactic\"}",
        "children": []
      },
      {
        "node_type": "ErrorNode",
        "state_text": null,
        "tactic": "```lean",
        "step_logprob": -1.4458732604980469,
        "cumulative_logprob": -1.4458732604980469,
        "depth": 1,
        "ppl": 4.245558002590287,
        "order_of_expansion": 5,
        "error_message": "{'hasSorry': False, 'hasUnsafe': False, 'parseError': \"<Pantograph>:1:0: expected '{' or tactic\"}",
        "children": []
      }
    ]
  }
}